{
	"name": "VibeColors Dark",
	"type": "dark",
	"colors": {
		// Editor colors
		"editor.background": "#1a1b26",
		"editor.foreground": "#c0caf5",
		"editorLineNumber.foreground": "#3b4261",
		"editorLineNumber.activeForeground": "#7aa2f7",
		"editorCursor.foreground": "#c0caf5",
		"editor.selectionBackground": "#33467c80",
		"editor.selectionHighlightBackground": "#3d59a140",
		"editor.wordHighlightBackground": "#32344a60",
		"editor.wordHighlightStrongBackground": "#32344a80",
		"editor.findMatchBackground": "#3d59a1",
		"editor.findMatchHighlightBackground": "#33467c",
		"editorBracketMatch.background": "#2d3f76",
		"editorBracketMatch.border": "#7aa2f7",
		"editorWhitespace.foreground": "#363b54",
		"editorIndentGuide.background1": "#363b54",
		"editorIndentGuide.activeBackground1": "#545c7e",
		"editorRuler.foreground": "#363b54",
		"editor.inactiveSelectionBackground": "#33467c40",
		"editor.lineHighlightBackground": "#24283b",
		"editor.lineHighlightBorder": "#24283b",
		"editorCursor.foregroundSecondary": "#9aa5ce",
		"editor.rangeHighlightBackground": "#2d3f7660",
		"editor.symbolHighlightBackground": "#33467c60",
		"editorLink.activeForeground": "#7aa2f7",
		"editor.snippetTabstopHighlightBackground": "#9ece6a40",
		"editor.snippetFinalTabstopHighlightBackground": "#e0af6840",
		"editorOverviewRuler.border": "#1a1b26",
		"editorOverviewRuler.currentContentForeground": "#7aa2f7",
		"editorOverviewRuler.incomingContentForeground": "#9ece6a",
		"editorOverviewRuler.findMatchForeground": "#e0af68",
		"editorOverviewRuler.rangeHighlightForeground": "#7aa2f780",
		"editorOverviewRuler.selectionHighlightForeground": "#33467c",
		"editorOverviewRuler.wordHighlightForeground": "#32344a",
		"editorOverviewRuler.wordHighlightStrongForeground": "#32344a",
		"editorOverviewRuler.modifiedForeground": "#e0af68",
		"editorOverviewRuler.addedForeground": "#9ece6a",
		"editorOverviewRuler.deletedForeground": "#f7768e",
		"editorOverviewRuler.errorForeground": "#f7768e",
		"editorOverviewRuler.warningForeground": "#e0af68",
		"editorOverviewRuler.infoForeground": "#7aa2f7",
		"editorError.foreground": "#f7768e",
		"editorWarning.foreground": "#e0af68",
		"editorInfo.foreground": "#7aa2f7",
		"editorHint.foreground": "#1abc9c",
		"problemsErrorIcon.foreground": "#f7768e",
		"problemsWarningIcon.foreground": "#e0af68",
		"problemsInfoIcon.foreground": "#7aa2f7",
		"editorUnnecessaryCode.border": "#565f89",
		"editorUnnecessaryCode.opacity": "#00000060",
		"editorGutter.background": "#1a1b26",
		"editorGutter.modifiedBackground": "#e0af68",
		"editorGutter.addedBackground": "#9ece6a",
		"editorGutter.deletedBackground": "#f7768e",
		"editorGutter.commentRangeForeground": "#565f89",
		"editorGutter.foldingControlForeground": "#9aa5ce",
		
		// Sidebar
		"sideBar.background": "#16161e",
		"sideBar.foreground": "#9aa5ce",
		"sideBarTitle.foreground": "#c0caf5",
		"sideBarSectionHeader.background": "#1a1b26",
		"sideBarSectionHeader.foreground": "#bb9af7",
		
		// Activity Bar
		"activityBar.background": "#16161e",
		"activityBar.foreground": "#9aa5ce",
		"activityBar.activeBorder": "#7aa2f7",
		"activityBar.activeBackground": "#24283b",
		"activityBarBadge.background": "#7aa2f7",
		"activityBarBadge.foreground": "#1a1b26",
		
		// Status Bar
		"statusBar.background": "#16161e",
		"statusBar.foreground": "#9aa5ce",
		"statusBar.noFolderBackground": "#16161e",
		"statusBarItem.activeBackground": "#2d3f76",
		"statusBarItem.hoverBackground": "#24283b",
		
		// Title Bar
		"titleBar.activeBackground": "#1a1b26",
		"titleBar.activeForeground": "#c0caf5",
		"titleBar.inactiveBackground": "#16161e",
		"titleBar.inactiveForeground": "#565f89",
		
		// Tabs
		"tab.activeBackground": "#1a1b26",
		"tab.activeForeground": "#c0caf5",
		"tab.activeBorder": "#7aa2f7",
		"tab.inactiveBackground": "#16161e",
		"tab.inactiveForeground": "#9aa5ce",
		"tab.border": "#24283b",
		
		// Panel
		"panel.background": "#1a1b26",
		"panel.border": "#24283b",
		"panelTitle.activeBorder": "#7aa2f7",
		"panelTitle.activeForeground": "#c0caf5",
		"panelTitle.inactiveForeground": "#9aa5ce",
		
		// Terminal
		"terminal.background": "#1a1b26",
		"terminal.foreground": "#c0caf5",
		"terminal.ansiBlack": "#414868",
		"terminal.ansiRed": "#f7768e",
		"terminal.ansiGreen": "#9ece6a",
		"terminal.ansiYellow": "#e0af68",
		"terminal.ansiBlue": "#7aa2f7",
		"terminal.ansiMagenta": "#bb9af7",
		"terminal.ansiCyan": "#7dcfff",
		"terminal.ansiWhite": "#c0caf5",
		"terminal.ansiBrightBlack": "#565f89",
		"terminal.ansiBrightRed": "#f7768e",
		"terminal.ansiBrightGreen": "#9ece6a",
		"terminal.ansiBrightYellow": "#e0af68",
		"terminal.ansiBrightBlue": "#7aa2f7",
		"terminal.ansiBrightMagenta": "#bb9af7",
		"terminal.ansiBrightCyan": "#7dcfff",
		"terminal.ansiBrightWhite": "#c0caf5",
		
		// Input
		"input.background": "#24283b",
		"input.border": "#3b4261",
		"input.foreground": "#c0caf5",
		"input.placeholderForeground": "#565f89",
		
		// Dropdown
		"dropdown.background": "#24283b",
		"dropdown.border": "#3b4261",
		"dropdown.foreground": "#c0caf5",
		
		// Button
		"button.background": "#7aa2f7",
		"button.foreground": "#1a1b26",
		"button.hoverBackground": "#89b4fa",
		
		// List
		"list.activeSelectionBackground": "#2d3f76",
		"list.activeSelectionForeground": "#c0caf5",
		"list.inactiveSelectionBackground": "#24283b",
		"list.hoverBackground": "#24283b",
		"list.focusBackground": "#2d3f76",
		
		// Tree
		"tree.indentGuidesStroke": "#3b4261",
		
		// Scrollbar
		"scrollbar.shadow": "#0000001a",
		"scrollbarSlider.background": "#3b426180",
		"scrollbarSlider.hoverBackground": "#565f8980",
		"scrollbarSlider.activeBackground": "#7aa2f780",
		
		// Badge
		"badge.background": "#7aa2f7",
		"badge.foreground": "#1a1b26",
		
		// Progress Bar
		"progressBar.background": "#7aa2f7",
		
		// Editor Widget
		"editorWidget.background": "#24283b",
		"editorWidget.border": "#3b4261",
		"editorSuggestWidget.background": "#24283b",
		"editorSuggestWidget.border": "#3b4261",
		"editorSuggestWidget.selectedBackground": "#2d3f76",
		
		// Peek View
		"peekView.border": "#7aa2f7",
		"peekViewEditor.background": "#24283b",
		"peekViewResult.background": "#24283b",
		"peekViewTitle.background": "#1a1b26",
		
		// Git
		"gitDecoration.modifiedResourceForeground": "#e0af68",
		"gitDecoration.deletedResourceForeground": "#f7768e",
		"gitDecoration.untrackedResourceForeground": "#9ece6a",
		"gitDecoration.conflictingResourceForeground": "#bb9af7",
		
		// Diff Editor
		"diffEditor.insertedTextBackground": "#9ece6a1a",
		"diffEditor.removedTextBackground": "#f7768e1a",
		
		// Merge Conflicts
		"merge.currentHeaderBackground": "#7aa2f740",
		"merge.incomingHeaderBackground": "#9ece6a40",
		"merge.border": "#3b4261",
		
		// Extensions
		"extensionButton.prominentBackground": "#7aa2f7",
		"extensionButton.prominentForeground": "#1a1b26",
		"extensionButton.prominentHoverBackground": "#89b4fa",
		
		// Notifications
		"notificationCenter.border": "#3b4261",
		"notificationCenterHeader.background": "#24283b",
		"notificationToast.border": "#3b4261",
		"notifications.background": "#24283b",
		"notifications.border": "#3b4261",
		"notifications.foreground": "#c0caf5",
		"notificationLink.foreground": "#7aa2f7",
		
		// Welcome Page
		"welcomePage.background": "#1a1b26",
		"walkThrough.embeddedEditorBackground": "#24283b",

		// Breadcrumbs
		"breadcrumb.foreground": "#9aa5ce",
		"breadcrumb.background": "#1a1b26",
		"breadcrumb.focusForeground": "#c0caf5",
		"breadcrumb.activeSelectionForeground": "#7aa2f7",
		"breadcrumbPicker.background": "#24283b",

		// Menu
		"menu.foreground": "#c0caf5",
		"menu.background": "#24283b",
		"menu.selectionForeground": "#c0caf5",
		"menu.selectionBackground": "#2d3f76",
		"menu.selectionBorder": "#7aa2f7",
		"menu.separatorBackground": "#3b4261",
		"menu.border": "#3b4261",

		// Minimap
		"minimap.background": "#1a1b26",
		"minimap.selectionHighlight": "#33467c",
		"minimap.errorHighlight": "#f7768e",
		"minimap.warningHighlight": "#e0af68",
		"minimap.findMatchHighlight": "#e0af68",
		"minimapSlider.background": "#3b426140",
		"minimapSlider.hoverBackground": "#565f8960",
		"minimapSlider.activeBackground": "#7aa2f760",
		"minimapGutter.addedBackground": "#9ece6a",
		"minimapGutter.modifiedBackground": "#e0af68",
		"minimapGutter.deletedBackground": "#f7768e",

		// Settings
		"settings.headerForeground": "#c0caf5",
		"settings.modifiedItemIndicator": "#7aa2f7",
		"settings.dropdownBackground": "#24283b",
		"settings.dropdownForeground": "#c0caf5",
		"settings.dropdownBorder": "#3b4261",
		"settings.dropdownListBorder": "#3b4261",
		"settings.checkboxBackground": "#24283b",
		"settings.checkboxForeground": "#c0caf5",
		"settings.checkboxBorder": "#3b4261",
		"settings.textInputBackground": "#24283b",
		"settings.textInputForeground": "#c0caf5",
		"settings.textInputBorder": "#3b4261",
		"settings.numberInputBackground": "#24283b",
		"settings.numberInputForeground": "#c0caf5",
		"settings.numberInputBorder": "#3b4261",

		// Quick Pick
		"quickInput.background": "#24283b",
		"quickInput.foreground": "#c0caf5",
		"quickInputTitle.background": "#1a1b26",
		"pickerGroup.border": "#3b4261",
		"pickerGroup.foreground": "#7aa2f7",

		// Keybinding
		"keybindingLabel.background": "#24283b",
		"keybindingLabel.foreground": "#c0caf5",
		"keybindingLabel.border": "#3b4261",
		"keybindingLabel.bottomBorder": "#565f89",

		// Debug
		"debugToolBar.background": "#24283b",
		"debugToolBar.border": "#3b4261",
		"debugExceptionWidget.border": "#f7768e",
		"debugExceptionWidget.background": "#24283b",

		// Chat
		"chat.requestBackground": "#24283b",
		"chat.requestBorder": "#3b4261",
		"chat.avatarBackground": "#7aa2f7",
		"chat.avatarForeground": "#1a1b26",

		// Testing
		"testing.iconFailed": "#f7768e",
		"testing.iconErrored": "#f7768e",
		"testing.iconPassed": "#9ece6a",
		"testing.runAction": "#7aa2f7",
		"testing.iconQueued": "#e0af68",
		"testing.iconUnset": "#9aa5ce",
		"testing.iconSkipped": "#565f89",
		"testing.peekBorder": "#f7768e",
		"testing.peekHeaderBackground": "#24283b",
		"testing.message.error.decorationForeground": "#f7768e",
		"testing.message.error.lineBackground": "#f7768e20",
		"testing.message.info.decorationForeground": "#7aa2f7",
		"testing.message.info.lineBackground": "#7aa2f720"
	},
	"tokenColors": [
		{
			"name": "Comment",
			"scope": [
				"comment",
				"punctuation.definition.comment"
			],
			"settings": {
				"fontStyle": "italic",
				"foreground": "#565f89"
			}
		},
		{
			"name": "Variables",
			"scope": [
				"variable",
				"string constant.other.placeholder"
			],
			"settings": {
				"foreground": "#c0caf5"
			}
		},
		{
			"name": "Colors",
			"scope": [
				"constant.other.color"
			],
			"settings": {
				"foreground": "#c0caf5"
			}
		},
		{
			"name": "Invalid",
			"scope": [
				"invalid",
				"invalid.illegal"
			],
			"settings": {
				"foreground": "#f7768e"
			}
		},
		{
			"name": "Keyword, Storage",
			"scope": [
				"keyword",
				"storage.type",
				"storage.modifier"
			],
			"settings": {
				"foreground": "#bb9af7"
			}
		},
		{
			"name": "Operator, Misc",
			"scope": [
				"keyword.control",
				"constant.other.color",
				"punctuation",
				"meta.tag",
				"punctuation.definition.tag",
				"punctuation.separator.inheritance.php",
				"punctuation.definition.tag.html",
				"punctuation.definition.tag.begin.html",
				"punctuation.definition.tag.end.html",
				"punctuation.section.embedded",
				"keyword.other.template",
				"keyword.other.substitution"
			],
			"settings": {
				"foreground": "#7dcfff"
			}
		},
		{
			"name": "Tag",
			"scope": [
				"entity.name.tag",
				"meta.tag.sgml",
				"markup.deleted.git_gutter"
			],
			"settings": {
				"foreground": "#f7768e"
			}
		},
		{
			"name": "Function, Special Method",
			"scope": [
				"entity.name.function",
				"meta.function-call",
				"variable.function",
				"support.function",
				"keyword.other.special-method"
			],
			"settings": {
				"foreground": "#7aa2f7"
			}
		},
		{
			"name": "Block Level Variables",
			"scope": [
				"meta.block variable.other"
			],
			"settings": {
				"foreground": "#f7768e"
			}
		},
		{
			"name": "Other Variable, String Link",
			"scope": [
				"support.other.variable",
				"string.other.link"
			],
			"settings": {
				"foreground": "#f7768e"
			}
		},
		{
			"name": "Number, Constant, Function Argument, Tag Attribute, Embedded",
			"scope": [
				"constant.numeric",
				"constant.language",
				"support.constant",
				"constant.character",
				"constant.escape",
				"variable.parameter",
				"keyword.other.unit",
				"keyword.other"
			],
			"settings": {
				"foreground": "#ff9e64"
			}
		},
		{
			"name": "String, Symbols, Inherited Class, Markup Heading",
			"scope": [
				"string",
				"constant.other.symbol",
				"constant.other.key",
				"entity.other.inherited-class",
				"markup.heading",
				"markup.inserted.git_gutter",
				"meta.group.braces.curly constant.other.object.key.js string.unquoted.label.js"
			],
			"settings": {
				"foreground": "#9ece6a"
			}
		},
		{
			"name": "Class, Support",
			"scope": [
				"entity.name",
				"support.type",
				"support.class",
				"support.other.namespace.use.php",
				"meta.use.php",
				"support.other.namespace.php",
				"markup.changed.git_gutter",
				"support.type.sys-types"
			],
			"settings": {
				"foreground": "#e0af68"
			}
		},
		{
			"name": "Entity Types",
			"scope": [
				"support.type"
			],
			"settings": {
				"foreground": "#9aa5ce"
			}
		},
		{
			"name": "CSS Class and Support",
			"scope": [
				"source.css support.type.property-name",
				"source.sass support.type.property-name",
				"source.scss support.type.property-name",
				"source.less support.type.property-name",
				"source.stylus support.type.property-name",
				"source.postcss support.type.property-name"
			],
			"settings": {
				"foreground": "#9aa5ce"
			}
		},
		{
			"name": "Sub-methods",
			"scope": [
				"entity.name.module.js",
				"variable.import.parameter.js",
				"variable.other.class.js"
			],
			"settings": {
				"foreground": "#f7768e"
			}
		},
		{
			"name": "Language methods",
			"scope": [
				"variable.language"
			],
			"settings": {
				"fontStyle": "italic",
				"foreground": "#f7768e"
			}
		},
		{
			"name": "entity.name.method.js",
			"scope": [
				"entity.name.method.js"
			],
			"settings": {
				"fontStyle": "italic",
				"foreground": "#7aa2f7"
			}
		},
		{
			"name": "meta.method.js",
			"scope": [
				"meta.class-method.js entity.name.function.js",
				"variable.function.constructor"
			],
			"settings": {
				"foreground": "#7aa2f7"
			}
		},
		{
			"name": "Attributes",
			"scope": [
				"entity.other.attribute-name"
			],
			"settings": {
				"foreground": "#bb9af7"
			}
		},
		{
			"name": "HTML Attributes",
			"scope": [
				"text.html.basic entity.other.attribute-name.html",
				"text.html.basic entity.other.attribute-name"
			],
			"settings": {
				"fontStyle": "italic",
				"foreground": "#e0af68"
			}
		},
		{
			"name": "CSS Classes",
			"scope": [
				"entity.other.attribute-name.class"
			],
			"settings": {
				"foreground": "#e0af68"
			}
		},
		{
			"name": "CSS ID's",
			"scope": [
				"source.sass keyword.control"
			],
			"settings": {
				"foreground": "#7aa2f7"
			}
		},
		{
			"name": "Inserted",
			"scope": [
				"markup.inserted"
			],
			"settings": {
				"foreground": "#9ece6a"
			}
		},
		{
			"name": "Deleted",
			"scope": [
				"markup.deleted"
			],
			"settings": {
				"foreground": "#f7768e"
			}
		},
		{
			"name": "Changed",
			"scope": [
				"markup.changed"
			],
			"settings": {
				"foreground": "#bb9af7"
			}
		},
		{
			"name": "Regular Expressions",
			"scope": [
				"string.regexp"
			],
			"settings": {
				"foreground": "#7dcfff"
			}
		},
		{
			"name": "Escape Characters",
			"scope": [
				"constant.character.escape"
			],
			"settings": {
				"foreground": "#7dcfff"
			}
		},
		{
			"name": "URL",
			"scope": [
				"*url*",
				"*link*",
				"*uri*"
			],
			"settings": {
				"fontStyle": "underline"
			}
		},
		{
			"name": "Decorators",
			"scope": [
				"tag.decorator.js entity.name.tag.js",
				"tag.decorator.js punctuation.definition.tag.js"
			],
			"settings": {
				"fontStyle": "italic",
				"foreground": "#7aa2f7"
			}
		},
		{
			"name": "ES7 Bind Operator",
			"scope": [
				"source.js constant.other.object.key.js string.unquoted.label.js"
			],
			"settings": {
				"fontStyle": "italic",
				"foreground": "#f7768e"
			}
		},
		{
			"name": "JSON Key - Level 0",
			"scope": [
				"source.json meta.structure.dictionary.json support.type.property-name.json"
			],
			"settings": {
				"foreground": "#bb9af7"
			}
		},
		{
			"name": "JSON Key - Level 1",
			"scope": [
				"source.json meta.structure.dictionary.json meta.structure.dictionary.value.json meta.structure.dictionary.json support.type.property-name.json"
			],
			"settings": {
				"foreground": "#e0af68"
			}
		},
		{
			"name": "JSON Key - Level 2",
			"scope": [
				"source.json meta.structure.dictionary.json meta.structure.dictionary.value.json meta.structure.dictionary.json meta.structure.dictionary.value.json meta.structure.dictionary.json support.type.property-name.json"
			],
			"settings": {
				"foreground": "#ff9e64"
			}
		},
		{
			"name": "JSON Key - Level 3",
			"scope": [
				"source.json meta.structure.dictionary.json meta.structure.dictionary.value.json meta.structure.dictionary.json meta.structure.dictionary.value.json meta.structure.dictionary.json meta.structure.dictionary.value.json meta.structure.dictionary.json support.type.property-name.json"
			],
			"settings": {
				"foreground": "#f7768e"
			}
		},
		{
			"name": "JSON Key - Level 4",
			"scope": [
				"source.json meta.structure.dictionary.json meta.structure.dictionary.value.json meta.structure.dictionary.json meta.structure.dictionary.value.json meta.structure.dictionary.json meta.structure.dictionary.value.json meta.structure.dictionary.json meta.structure.dictionary.value.json meta.structure.dictionary.json support.type.property-name.json"
			],
			"settings": {
				"foreground": "#ff9e64"
			}
		},
		{
			"name": "JSON Key - Level 5",
			"scope": [
				"source.json meta.structure.dictionary.json meta.structure.dictionary.value.json meta.structure.dictionary.json meta.structure.dictionary.value.json meta.structure.dictionary.json meta.structure.dictionary.value.json meta.structure.dictionary.json meta.structure.dictionary.value.json meta.structure.dictionary.json meta.structure.dictionary.value.json meta.structure.dictionary.json support.type.property-name.json"
			],
			"settings": {
				"foreground": "#7aa2f7"
			}
		},
		{
			"name": "JSON Key - Level 6",
			"scope": [
				"source.json meta.structure.dictionary.json meta.structure.dictionary.value.json meta.structure.dictionary.json meta.structure.dictionary.value.json meta.structure.dictionary.json meta.structure.dictionary.value.json meta.structure.dictionary.json meta.structure.dictionary.value.json meta.structure.dictionary.json meta.structure.dictionary.value.json meta.structure.dictionary.json meta.structure.dictionary.value.json meta.structure.dictionary.json support.type.property-name.json"
			],
			"settings": {
				"foreground": "#f7768e"
			}
		},
		{
			"name": "JSON Key - Level 7",
			"scope": [
				"source.json meta.structure.dictionary.json meta.structure.dictionary.value.json meta.structure.dictionary.json meta.structure.dictionary.value.json meta.structure.dictionary.json meta.structure.dictionary.value.json meta.structure.dictionary.json meta.structure.dictionary.value.json meta.structure.dictionary.json meta.structure.dictionary.value.json meta.structure.dictionary.json meta.structure.dictionary.value.json meta.structure.dictionary.json meta.structure.dictionary.value.json meta.structure.dictionary.json support.type.property-name.json"
			],
			"settings": {
				"foreground": "#bb9af7"
			}
		},
		{
			"name": "JSON Key - Level 8",
			"scope": [
				"source.json meta.structure.dictionary.json meta.structure.dictionary.value.json meta.structure.dictionary.json meta.structure.dictionary.value.json meta.structure.dictionary.json meta.structure.dictionary.value.json meta.structure.dictionary.json meta.structure.dictionary.value.json meta.structure.dictionary.json meta.structure.dictionary.value.json meta.structure.dictionary.json meta.structure.dictionary.value.json meta.structure.dictionary.json meta.structure.dictionary.value.json meta.structure.dictionary.json meta.structure.dictionary.value.json meta.structure.dictionary.json support.type.property-name.json"
			],
			"settings": {
				"foreground": "#9ece6a"
			}
		},
		{
			"name": "Markdown - Plain",
			"scope": [
				"text.html.markdown",
				"punctuation.definition.list_item.markdown"
			],
			"settings": {
				"foreground": "#c0caf5"
			}
		},
		{
			"name": "Markdown - Markup Raw Inline",
			"scope": [
				"text.html.markdown markup.inline.raw.markdown"
			],
			"settings": {
				"foreground": "#bb9af7"
			}
		},
		{
			"name": "Markdown - Markup Raw Inline Punctuation",
			"scope": [
				"text.html.markdown markup.inline.raw.markdown punctuation.definition.raw.markdown"
			],
			"settings": {
				"foreground": "#565f89"
			}
		},
		{
			"name": "Markdown - Heading",
			"scope": [
				"markdown.heading",
				"markup.heading | markup.heading entity.name",
				"markup.heading.markdown punctuation.definition.heading.markdown"
			],
			"settings": {
				"foreground": "#9ece6a"
			}
		},
		{
			"name": "Markup - Italic",
			"scope": [
				"markup.italic"
			],
			"settings": {
				"fontStyle": "italic",
				"foreground": "#f7768e"
			}
		},
		{
			"name": "Markup - Bold",
			"scope": [
				"markup.bold",
				"markup.bold string"
			],
			"settings": {
				"fontStyle": "bold",
				"foreground": "#f7768e"
			}
		},
		{
			"name": "Markup - Bold-Italic",
			"scope": [
				"markup.bold markup.italic",
				"markup.italic markup.bold",
				"markup.quote markup.bold",
				"markup.bold markup.italic string",
				"markup.italic markup.bold string",
				"markup.quote markup.bold string"
			],
			"settings": {
				"fontStyle": "bold",
				"foreground": "#f7768e"
			}
		},
		{
			"name": "Markup - Underline",
			"scope": [
				"markup.underline"
			],
			"settings": {
				"fontStyle": "underline",
				"foreground": "#ff9e64"
			}
		},
		{
			"name": "Markdown - Blockquote",
			"scope": [
				"markup.quote punctuation.definition.blockquote.markdown"
			],
			"settings": {
				"foreground": "#565f89"
			}
		},
		{
			"name": "Markup - Quote",
			"scope": [
				"markup.quote"
			],
			"settings": {
				"fontStyle": "italic"
			}
		},
		{
			"name": "Markdown - Link",
			"scope": [
				"string.other.link.title.markdown"
			],
			"settings": {
				"foreground": "#7aa2f7"
			}
		},
		{
			"name": "Markdown - Link Description",
			"scope": [
				"string.other.link.description.title.markdown"
			],
			"settings": {
				"foreground": "#bb9af7"
			}
		},
		{
			"name": "Markdown - Link Anchor",
			"scope": [
				"constant.other.reference.link.markdown"
			],
			"settings": {
				"foreground": "#e0af68"
			}
		},
		{
			"name": "Markup - Raw Block",
			"scope": [
				"markup.raw.block"
			],
			"settings": {
				"foreground": "#bb9af7"
			}
		},
		{
			"name": "Markdown - Raw Block Fenced",
			"scope": [
				"markup.raw.block.fenced.markdown"
			],
			"settings": {
				"foreground": "#414868"
			}
		},
		{
			"name": "Markdown - Fenced Bode Block",
			"scope": [
				"punctuation.definition.fenced.markdown"
			],
			"settings": {
				"foreground": "#414868"
			}
		},
		{
			"name": "Markdown - Fenced Bode Block Variable",
			"scope": [
				"markup.raw.block.fenced.markdown",
				"variable.language.fenced.markdown",
				"punctuation.section.class.end"
			],
			"settings": {
				"foreground": "#c0caf5"
			}
		},
		{
			"name": "Markdown - Fenced Language",
			"scope": [
				"variable.language.fenced.markdown"
			],
			"settings": {
				"foreground": "#565f89"
			}
		},
		{
			"name": "Markdown - Separator",
			"scope": [
				"meta.separator"
			],
			"settings": {
				"fontStyle": "bold",
				"foreground": "#565f89"
			}
		},
		{
			"name": "Markup - Table",
			"scope": [
				"markup.table"
			],
			"settings": {
				"foreground": "#c0caf5"
			}
		},
		{
			"name": "Python - Self Parameter",
			"scope": [
				"variable.parameter.function.language.special.self.python"
			],
			"settings": {
				"fontStyle": "italic",
				"foreground": "#f7768e"
			}
		},
		{
			"name": "Python - Magic Methods",
			"scope": [
				"support.function.magic.python"
			],
			"settings": {
				"fontStyle": "italic",
				"foreground": "#bb9af7"
			}
		},
		{
			"name": "Python - Decorators",
			"scope": [
				"entity.name.function.decorator.python",
				"punctuation.definition.decorator.python"
			],
			"settings": {
				"foreground": "#e0af68"
			}
		},
		{
			"name": "Python - Function Calls",
			"scope": [
				"meta.function-call.python"
			],
			"settings": {
				"foreground": "#7aa2f7"
			}
		},
		{
			"name": "TypeScript - Types",
			"scope": [
				"entity.name.type.typescript",
				"entity.name.type.interface.typescript",
				"support.type.primitive.typescript",
				"keyword.type.typescript"
			],
			"settings": {
				"foreground": "#1abc9c"
			}
		},
		{
			"name": "TypeScript - Type Parameters",
			"scope": [
				"entity.name.type.parameter.typescript"
			],
			"settings": {
				"foreground": "#bb9af7"
			}
		},
		{
			"name": "TypeScript - Interfaces",
			"scope": [
				"entity.name.type.interface.typescript"
			],
			"settings": {
				"foreground": "#1abc9c"
			}
		},
		{
			"name": "React - Component Names",
			"scope": [
				"support.class.component.tsx",
				"support.class.component.jsx"
			],
			"settings": {
				"foreground": "#1abc9c"
			}
		},
		{
			"name": "React - JSX Tags",
			"scope": [
				"entity.name.tag.tsx",
				"entity.name.tag.jsx"
			],
			"settings": {
				"foreground": "#f7768e"
			}
		},
		{
			"name": "React - JSX Attributes",
			"scope": [
				"entity.other.attribute-name.tsx",
				"entity.other.attribute-name.jsx"
			],
			"settings": {
				"fontStyle": "italic",
				"foreground": "#e0af68"
			}
		},
		{
			"name": "Go - Types",
			"scope": [
				"entity.name.type.go"
			],
			"settings": {
				"foreground": "#1abc9c"
			}
		},
		{
			"name": "Go - Package Names",
			"scope": [
				"entity.name.package.go"
			],
			"settings": {
				"foreground": "#e0af68"
			}
		},
		{
			"name": "Rust - Types",
			"scope": [
				"entity.name.type.rust",
				"storage.type.rust"
			],
			"settings": {
				"foreground": "#1abc9c"
			}
		},
		{
			"name": "Rust - Lifetime Parameters",
			"scope": [
				"storage.modifier.lifetime.rust",
				"entity.name.type.lifetime.rust"
			],
			"settings": {
				"fontStyle": "italic",
				"foreground": "#bb9af7"
			}
		},
		{
			"name": "Rust - Macros",
			"scope": [
				"entity.name.function.macro.rust"
			],
			"settings": {
				"foreground": "#e0af68"
			}
		},
		{
			"name": "C/C++ - Preprocessor",
			"scope": [
				"keyword.control.directive.cpp",
				"keyword.control.directive.c"
			],
			"settings": {
				"foreground": "#bb9af7"
			}
		},
		{
			"name": "C/C++ - Types",
			"scope": [
				"storage.type.built-in.cpp",
				"storage.type.built-in.c"
			],
			"settings": {
				"foreground": "#1abc9c"
			}
		},
		{
			"name": "Java - Annotations",
			"scope": [
				"storage.type.annotation.java"
			],
			"settings": {
				"foreground": "#e0af68"
			}
		},
		{
			"name": "Java - Types",
			"scope": [
				"storage.type.java",
				"storage.type.generic.java"
			],
			"settings": {
				"foreground": "#1abc9c"
			}
		},
		{
			"name": "PHP - Variables",
			"scope": [
				"variable.other.php",
				"punctuation.definition.variable.php"
			],
			"settings": {
				"foreground": "#f7768e"
			}
		},
		{
			"name": "PHP - Constants",
			"scope": [
				"constant.other.php"
			],
			"settings": {
				"foreground": "#bb9af7"
			}
		},
		{
			"name": "SQL - Keywords",
			"scope": [
				"keyword.other.sql"
			],
			"settings": {
				"foreground": "#bb9af7"
			}
		},
		{
			"name": "YAML - Keys",
			"scope": [
				"entity.name.tag.yaml"
			],
			"settings": {
				"foreground": "#7aa2f7"
			}
		},
		{
			"name": "YAML - Values",
			"scope": [
				"string.unquoted.yaml"
			],
			"settings": {
				"foreground": "#9ece6a"
			}
		},
		{
			"name": "Docker - Instructions",
			"scope": [
				"keyword.other.special-method.dockerfile"
			],
			"settings": {
				"foreground": "#bb9af7"
			}
		},
		{
			"name": "Shell - Variables",
			"scope": [
				"variable.other.readwrite.shell",
				"punctuation.definition.variable.shell"
			],
			"settings": {
				"foreground": "#f7768e"
			}
		},
		{
			"name": "Git - Commit Hash",
			"scope": [
				"constant.other.hash.git-commit"
			],
			"settings": {
				"foreground": "#bb9af7"
			}
		},
		{
			"name": "Git - Modified Files",
			"scope": [
				"markup.changed.git"
			],
			"settings": {
				"foreground": "#e0af68"
			}
		},
		{
			"name": "Log Levels - Error",
			"scope": [
				"markup.error.log"
			],
			"settings": {
				"foreground": "#f7768e"
			}
		},
		{
			"name": "Log Levels - Warning",
			"scope": [
				"markup.warning.log"
			],
			"settings": {
				"foreground": "#e0af68"
			}
		},
		{
			"name": "Log Levels - Info",
			"scope": [
				"markup.info.log"
			],
			"settings": {
				"foreground": "#7aa2f7"
			}
		}
	]
}
